dask_dirac/__init__.py
dask_dirac/_dask.py
dask_dirac/_dirac.py
dask_dirac/_version.py
dask_dirac/cli.py
dask_dirac/py.typed
dask_dirac/templates/__init__.py
dask_dirac/templates/jdl.j2
dask_dirac/templates/submit_command.j2
dask_dirac-2025.3.1.dist-info/entry_points.txt
dask_dirac-2025.3.1.dist-info/licenses/LICENSE
dask_dirac-2025.3.1.dist-info/WHEEL
dask_dirac-2025.3.1.dist-info/METADATA
dask_dirac-2025.3.1.dist-info/RECORD
