Metadata-Version: 2.4
Name: dask_dirac
Version: 2025.3.1
Summary: DIRAC Executor for Dask
Author-email: Luke Kreczko <kreczko@cern.ch>, Sam Eriksen <sam.eriksen@bristol.ac.uk>
Maintainer-email: The SWIFT-HEP admins <UK-SwiftHep@cern.ch>
Requires-Python: >=3.9
Classifier: License :: OSI Approved :: BSD License
Classifier: Topic :: Scientific/Engineering
Classifier: Intended Audience :: Science/Research
Classifier: Intended Audience :: Developers
Classifier: Operating System :: OS Independent
Classifier: License :: OSI Approved :: BSD License
Classifier: Programming Language :: Python
Classifier: Programming Language :: Python :: 3
Classifier: Programming Language :: Python :: 3.9
Classifier: Programming Language :: Python :: 3.10
Classifier: Programming Language :: Python :: 3.11
Classifier: Development Status :: 3 - Alpha
License-File: LICENSE
Requires-Dist: dask
Requires-Dist: dask_jobqueue
Requires-Dist: jinja2
Requires-Dist: requests
Requires-Dist: typer
Requires-Dist: pandas
Requires-Dist: pytest >=6 ; extra == "dev"
Requires-Dist: Sphinx>=4.0 ; extra == "docs"
Requires-Dist: myst_parser>=0.13 ; extra == "docs"
Requires-Dist: sphinx-book-theme>=0.1.0 ; extra == "docs"
Requires-Dist: sphinx_copybutton ; extra == "docs"
Requires-Dist: pytest >=6 ; extra == "test"
Project-URL: homepage, https://github.com/SWIFT-HEP/dask-dirac
Provides-Extra: dev
Provides-Extra: docs
Provides-Extra: test
